LICENSE
MANIFEST.in
README.rst
setup.py
bitcoins/__init__.py
bitcoins/api.py
bitcoins.egg-info/PKG-INFO
bitcoins.egg-info/SOURCES.txt
bitcoins.egg-info/dependency_links.txt
bitcoins.egg-info/top_level.txt