Metadata-Version: 1.1
Name: bitcoins
Version: 0.0.0
Summary: Python Bitcoins for Humans.
Home-page: https://github.com/KenanY/bitcoins
Author: Kenan Yildirim
Author-email: kenan@kenany.me
License: Copyright © 2012 Kenan Yildirim.
